ImageAI/DataProcessor.py
ImageAI/DatabaseHandler.py
ImageAI/__init__.py
SimpleAI_Image/DataProcessor.py
SimpleAI_Image/DatabaseHandler.py
SimpleAI_Image/__init__.py
tests/__init__.py
SimpleAI_Image-0.1.8.dist-info/METADATA
SimpleAI_Image-0.1.8.dist-info/WHEEL
SimpleAI_Image-0.1.8.dist-info/top_level.txt
SimpleAI_Image-0.1.8.dist-info/RECORD
